LICENSE
README.md
setup.py
pingexcelutil/ExcelFormatter.py
pingexcelutil/ExcelReader.py
pingexcelutil/Logger.py
pingexcelutil/_Util.py
pingexcelutil/__init__.py
pingexcelutil.egg-info/PKG-INFO
pingexcelutil.egg-info/SOURCES.txt
pingexcelutil.egg-info/dependency_links.txt
pingexcelutil.egg-info/requires.txt
pingexcelutil.egg-info/top_level.txt